azure/cognitiveservices/speech/Microsoft.CognitiveServices.Speech.core.dll
azure/cognitiveservices/speech/Microsoft.CognitiveServices.Speech.extension.audio.sys.dll
azure/cognitiveservices/speech/Microsoft.CognitiveServices.Speech.extension.codec.dll
azure/cognitiveservices/speech/Microsoft.CognitiveServices.Speech.extension.kws.dll
azure/cognitiveservices/speech/Microsoft.CognitiveServices.Speech.extension.kws.ort.dll
azure/cognitiveservices/speech/Microsoft.CognitiveServices.Speech.extension.lu.dll
azure/cognitiveservices/speech/__init__.py
azure/cognitiveservices/speech/audio.py
azure/cognitiveservices/speech/dialog.py
azure/cognitiveservices/speech/enums.py
azure/cognitiveservices/speech/intent.py
azure/cognitiveservices/speech/interop.py
azure/cognitiveservices/speech/languageconfig.py
azure/cognitiveservices/speech/properties.py
azure/cognitiveservices/speech/speech.py
azure/cognitiveservices/speech/transcription.py
azure/cognitiveservices/speech/translation.py
azure/cognitiveservices/speech/version.py
azure/cognitiveservices/speech/diagnostics/__init__.py
azure/cognitiveservices/speech/diagnostics/logging.py
azure_cognitiveservices_speech-1.46.0.dist-info/licenses/licensefiles/speech/LICENSE.md
azure_cognitiveservices_speech-1.46.0.dist-info/licenses/licensefiles/speech/REDIST.txt
azure_cognitiveservices_speech-1.46.0.dist-info/licenses/licensefiles/speech/ThirdPartyNotices.md
azure_cognitiveservices_speech-1.46.0.dist-info/METADATA
azure_cognitiveservices_speech-1.46.0.dist-info/WHEEL
azure_cognitiveservices_speech-1.46.0.dist-info/top_level.txt
azure_cognitiveservices_speech-1.46.0.dist-info/RECORD
