Metadata-Version: 2.4
Name: azure-cognitiveservices-speech
Version: 1.46.0
Summary: Microsoft Cognitive Services Speech SDK for Python
Author: Microsoft
Classifier: Development Status :: 5 - Production/Stable
Classifier: Intended Audience :: Developers
Classifier: License :: Other/Proprietary License
Classifier: Operating System :: POSIX :: Linux
Classifier: Operating System :: MacOS :: MacOS X
Classifier: Operating System :: Microsoft :: Windows
Classifier: Programming Language :: Python
Classifier: Topic :: Scientific/Engineering
Classifier: Topic :: Software Development :: Libraries :: Python Modules
Requires-Python: >=3.7
License-File: licensefiles/speech/REDIST.txt
License-File: licensefiles/speech/ThirdPartyNotices.md
License-File: licensefiles/speech/LICENSE.md
Requires-Dist: azure-core>=1.31.0
Dynamic: classifier
Dynamic: license-file
Dynamic: requires-dist
Dynamic: requires-python
